ty_server/__init__.py
ty_server-0.0.0a1.dist-info/WHEEL
ty_server-0.0.0a1.dist-info/entry_points.txt
ty_server-0.0.0a1.dist-info/METADATA
ty_server-0.0.0a1.dist-info/RECORD
